sigint_examples/__init__.py
sigint_examples/basic_workflow.py
sigint_examples/plotting.py
sigint_examples/processing.py
sigint_examples/simulation.py
sigint_examples-0.1.2.dist-info/licenses/LICENSE
sigint_examples-0.1.2.dist-info/METADATA
sigint_examples-0.1.2.dist-info/WHEEL
sigint_examples-0.1.2.dist-info/entry_points.txt
sigint_examples-0.1.2.dist-info/top_level.txt
sigint_examples-0.1.2.dist-info/RECORD
