Metadata-Version: 2.4
Name: sigint_examples
Version: 0.1.2
Summary: Python SIGINT simulations and analysis tools
Author-email: Jackson Walters <jackson@jacksonwalters.com>
License: MIT License
Project-URL: Homepage, https://github.com/jacksonwalters/SIGINT
Classifier: Programming Language :: Python :: 3
Classifier: License :: OSI Approved :: MIT License
Classifier: Operating System :: OS Independent
Requires-Python: >=3.10
License-File: LICENSE
Dynamic: license-file
